yellow_banana/__init__.py
yellow_banana/main.py
yellow_banana-0.1.1.dist-info/LICENSE
yellow_banana-0.1.1.dist-info/METADATA
yellow_banana-0.1.1.dist-info/WHEEL
yellow_banana-0.1.1.dist-info/entry_points.txt
yellow_banana-0.1.1.dist-info/top_level.txt
yellow_banana-0.1.1.dist-info/RECORD
