Metadata-Version: 2.1
Name: yellow-banana
Version: 0.1.1
Summary: A simple CLI tool.
Home-page: https://github.com/bloominstituteoftechnology/yellow_banana
Author: Gabriel Cabrejas
Author-email: gabriel@cabrejas.net
License: UNKNOWN
Platform: UNKNOWN
Classifier: Programming Language :: Python :: 3
Classifier: License :: OSI Approved :: MIT License
Classifier: Operating System :: OS Independent
Requires-Python: >=3.6
License-File: LICENSE
Requires-Dist: openai
